cxtgeo.py
cxtgeoPYTHON_wrap.c
xtgeo/__init__.py
xtgeo/_cxtgeo.cp312-win_amd64.pyd
xtgeo/_internal.cp312-win_amd64.pyd
xtgeo/common/__init__.py
xtgeo/common/_angles.py
xtgeo/common/_xyz_enum.py
xtgeo/common/calc.py
xtgeo/common/constants.py
xtgeo/common/exceptions.py
xtgeo/common/log.py
xtgeo/common/sys.py
xtgeo/common/types.py
xtgeo/common/version.py
xtgeo/common/xtgeo_dialog.py
xtgeo/cube/__init__.py
xtgeo/cube/_cube_export.py
xtgeo/cube/_cube_import.py
xtgeo/cube/_cube_roxapi.py
xtgeo/cube/_cube_utils.py
xtgeo/cube/_cube_window_attributes.py
xtgeo/cube/cube1.py
xtgeo/grid3d/__init__.py
xtgeo/grid3d/_ecl_grid.py
xtgeo/grid3d/_ecl_inte_head.py
xtgeo/grid3d/_ecl_logi_head.py
xtgeo/grid3d/_ecl_output_file.py
xtgeo/grid3d/_egrid.py
xtgeo/grid3d/_find_gridprop_in_eclrun.py
xtgeo/grid3d/_grdecl_format.py
xtgeo/grid3d/_grdecl_grid.py
xtgeo/grid3d/_grid3d.py
xtgeo/grid3d/_grid3d_fence.py
xtgeo/grid3d/_grid3d_utils.py
xtgeo/grid3d/_grid_boundary.py
xtgeo/grid3d/_grid_etc1.py
xtgeo/grid3d/_grid_export.py
xtgeo/grid3d/_grid_hybrid.py
xtgeo/grid3d/_grid_import.py
xtgeo/grid3d/_grid_import_ecl.py
xtgeo/grid3d/_grid_import_roff.py
xtgeo/grid3d/_grid_import_xtgcpgeom.py
xtgeo/grid3d/_grid_refine.py
xtgeo/grid3d/_grid_roxapi.py
xtgeo/grid3d/_grid_translate_coords.py
xtgeo/grid3d/_grid_wellzone.py
xtgeo/grid3d/_gridprop_export.py
xtgeo/grid3d/_gridprop_import_eclrun.py
xtgeo/grid3d/_gridprop_import_grdecl.py
xtgeo/grid3d/_gridprop_import_roff.py
xtgeo/grid3d/_gridprop_import_xtgcpprop.py
xtgeo/grid3d/_gridprop_lowlevel.py
xtgeo/grid3d/_gridprop_op1.py
xtgeo/grid3d/_gridprop_roxapi.py
xtgeo/grid3d/_gridprop_value_init.py
xtgeo/grid3d/_gridprops_import_eclrun.py
xtgeo/grid3d/_gridprops_import_roff.py
xtgeo/grid3d/_roff_grid.py
xtgeo/grid3d/_roff_parameter.py
xtgeo/grid3d/grid.py
xtgeo/grid3d/grid_properties.py
xtgeo/grid3d/grid_property.py
xtgeo/grid3d/types.py
xtgeo/interfaces/rms/__init__.py
xtgeo/interfaces/rms/_regular_surface.py
xtgeo/interfaces/rms/_rms_base.py
xtgeo-4.16.2.dist-info/METADATA
xtgeo-4.16.2.dist-info/WHEEL
xtgeo-4.16.2.dist-info/licenses/LICENSE.md
xtgeo-4.16.2.dist-info/RECORD
