Metadata-Version: 2.2
Name: xtgeo
Version: 4.16.2
Summary: XTGeo is a Python library for 3D grids, surfaces, wells, etc
Keywords: grids,surfaces,wells,cubes
Author-Email: Equinor <fg_fmu-atlas@equinor.com>
License: LGPL-3.0
Classifier: Development Status :: 5 - Production/Stable
Classifier: Intended Audience :: Developers
Classifier: Intended Audience :: Science/Research
Classifier: License :: OSI Approved :: GNU Lesser General Public License v3 (LGPLv3)
Classifier: Operating System :: POSIX :: Linux
Classifier: Operating System :: Microsoft :: Windows
Classifier: Operating System :: MacOS
Classifier: Natural Language :: English
Classifier: Programming Language :: Python
Classifier: Programming Language :: Python :: 3.10
Classifier: Programming Language :: Python :: 3.11
Classifier: Programming Language :: Python :: 3.12
Classifier: Programming Language :: Python :: 3.13
Classifier: Topic :: Scientific/Engineering
Classifier: Topic :: Scientific/Engineering :: Physics
Classifier: Topic :: Software Development :: Libraries
Classifier: Topic :: Utilities
Project-URL: Homepage, https://github.com/equinor/xtgeo
Project-URL: Repository, https://github.com/equinor/xtgeo
Project-URL: Issues, https://github.com/equinor/xtgeo/issues
Project-URL: Documentation, https://xtgeo.readthedocs.io
Requires-Python: >=3.10
Requires-Dist: deprecation
Requires-Dist: gstools
Requires-Dist: h5py>=3
Requires-Dist: hdf5plugin>=2.3
Requires-Dist: joblib
Requires-Dist: matplotlib>=3.3
Requires-Dist: numpy
Requires-Dist: pandas<3.0.0,>=1.1
Requires-Dist: pyarrow
Requires-Dist: resfo>=5
Requires-Dist: roffio>=0.0.2
Requires-Dist: scipy>=1.5
Requires-Dist: segyio>1.8.0
Requires-Dist: shapely>=1.6.2
Requires-Dist: tables
Requires-Dist: typing_extensions
Requires-Dist: xtgeoviz
Provides-Extra: dev
Requires-Dist: clang-format; extra == "dev"
Requires-Dist: cmake-format; extra == "dev"
Requires-Dist: coverage>=4.1; extra == "dev"
Requires-Dist: hypothesis; extra == "dev"
Requires-Dist: mypy; extra == "dev"
Requires-Dist: pandas-stubs; extra == "dev"
Requires-Dist: psutil; extra == "dev"
Requires-Dist: pydocstyle; extra == "dev"
Requires-Dist: pytest; extra == "dev"
Requires-Dist: pytest-benchmark; extra == "dev"
Requires-Dist: pytest-cov; extra == "dev"
Requires-Dist: pytest-mock; extra == "dev"
Requires-Dist: pytest-runner; extra == "dev"
Requires-Dist: pytest-snapshot; extra == "dev"
Requires-Dist: pytest-xdist; extra == "dev"
Requires-Dist: ruff; extra == "dev"
Provides-Extra: docs
Requires-Dist: autoclasstoc; extra == "docs"
Requires-Dist: myst-parser; extra == "docs"
Requires-Dist: pydocstyle; extra == "docs"
Requires-Dist: sphinx; extra == "docs"
Requires-Dist: sphinx-autodoc-typehints; extra == "docs"
Requires-Dist: sphinx-rtd-theme; extra == "docs"
Requires-Dist: sphinx-tabs<3.4.5; extra == "docs"
Requires-Dist: sphinx-toolbox>=3.5.0; extra == "docs"
